Workbook

Sheet Dashboard
AD5: =_xlfn.CONCAT(petrobras_dados!D2,"%") -> 47,63%
AD6: =_xlfn.CONCAT(petrobras_dados!D3,"%") -> 46,23%
AD7: =_xlfn.CONCAT(petrobras_dados!D4,"%") -> 29,27%
AD8: =_xlfn.CONCAT(petrobras_dados!D5,"%") -> 22,23%
A9: =IF(petrobras_dados!D2>petrobras_dados!E2,"▲","▼")&" "&TEXT(ABS(petrobras_dados!D2-petrobras_dados!E2),"0,00")&"pp vs 2024" -> ▼ 2,58pp vs 2024 | D9: =IF(petrobras_dados!D3>petrobras_dados!E3,"▲","▼")&" "&TEXT(ABS(petrobras_dados!D3-petrobras_dados!E3),"0,00")&"pp vs 2024" -> ▲ 4,62pp vs 2024 | G9: =IF(petrobras_dados!D4>petrobras_dados!E4,"▲","▼")&" "&TEXT(ABS(petrobras_dados!D4-petrobras_dados!E4),"0,00")&"pp vs 2024" -> ▲ 1,32pp vs 2024 | J9: =IF(petrobras_dados!D5>petrobras_dados!E5,"▲","▼")&" "&TEXT(ABS(petrobras_dados!D5-petrobras_dados!E5),"0,00")&"pp vs 2024" -> ▲ 14,69pp vs 2024 | AD9: =_xlfn.CONCAT(petrobras_dados!D6,"%") -> 26,49%
AD10: =_xlfn.CONCAT(petrobras_dados!D7,"%") -> 9,04%
AD11: =_xlfn.CONCAT(petrobras_dados!D8,"%") -> 14,21%
AD12: =_xlfn.CONCAT(petrobras_dados!D9,"%") -> 19,39%
AD13: =_xlfn.CONCAT(petrobras_dados!D10,"X") -> 0,71X
AD14: =_xlfn.CONCAT(petrobras_dados!D11,"X") -> 0,26X
AD15: =_xlfn.CONCAT(petrobras_dados!D12,"X") -> 0,31X
AD16: =_xlfn.CONCAT(petrobras_dados!D13,"X") -> 0,92X
A17: =IF(petrobras_dados!D6>petrobras_dados!E6,"▲","▼")&" "&TEXT(ABS(petrobras_dados!D6-petrobras_dados!E6),"0,00")&"pp vs 2024" -> ▲ 16,42pp vs 2024 | D17: =IF(petrobras_dados!D7>petrobras_dados!E7,"▲","▼")&" "&TEXT(ABS(petrobras_dados!D7-petrobras_dados!E7),"0,00")&"pp vs 2024" -> ▲ 5,75pp vs 2024 | G17: =IF(petrobras_dados!D8>petrobras_dados!E8,"▲","▼")&" "&TEXT(ABS(petrobras_dados!D8-petrobras_dados!E8),"0,00")&"pp vs 2024" -> ▼ 0,54pp vs 2024 | J17: =IF(petrobras_dados!D9>petrobras_dados!E9,"▲","▼")&" "&TEXT(ABS(petrobras_dados!D9-petrobras_dados!E9),"0,00")&"pp vs 2024" -> ▼ 0,37pp vs 2024
A25: =IF(petrobras_dados!D10>petrobras_dados!E10,"▲","▼")&" "&TEXT(ABS(petrobras_dados!D10-petrobras_dados!E10),"0,00")&"pp vs 2024" -> ▲ 0,02pp vs 2024 | D25: =IF(petrobras_dados!D11>petrobras_dados!E11,"▲","▼")&" "&TEXT(ABS(petrobras_dados!D11-petrobras_dados!E11),"0,00")&"pp vs 2024" -> ▲ 0,02pp vs 2024 | G25: =IF(petrobras_dados!D12>petrobras_dados!E12,"▲","▼")&" "&TEXT(ABS(petrobras_dados!D12-petrobras_dados!E12),"0,00")&"pp vs 2024" -> ▼ 0,02pp vs 2024 | J25: =IF(petrobras_dados!D13>petrobras_dados!E13,"▲","▼")&" "&TEXT(ABS(petrobras_dados!D13-petrobras_dados!E13),"0,00")&"pp vs 2024" -> ▼ 0,10pp vs 2024

Sheet petrobras_dados
A1: Column1 | B1: indicador | C1: categoria | D1: valor_2025 | E1: valor_2024
A2: 0 | B2: Margem Bruta | C2: Lucratividade | D2: 47.63 | E2: 50.21
A3: 1 | B3: Margem EBITDA | C3: Lucratividade | D3: 46.23 | E3: 41.61
A4: 2 | B4: Margem Operacional | C4: Lucratividade | D4: 29.27 | E4: 27.95
A5: 3 | B5: Margem Lķquida | C5: Lucratividade | D5: 22.23 | E5: 7.54
A6: 4 | B6: ROE | C6: Retorno | D6: 26.49 | E6: 10.07
A7: 5 | B7: ROA | C7: Retorno | D7: 9.04 | E7: 3.29
A8: 6 | B8: ROCE | C8: Retorno | D8: 14.21 | E8: 14.75
A9: 7 | B9: ROIC | C9: Retorno | D9: 19.39 | E9: 19.76
A10: 8 | B10: Liquidez Corrente | C10: Liquidez | D10: 0.71 | E10: 0.69
A11: 9 | B11: Liquidez Imediata | C11: Liquidez | D11: 0.26 | E11: 0.24
A12: 10 | B12: Debt Ratio | C12: Alavancagem | D12: 0.31 | E12: 0.33
A13: 11 | B13: Debt to Equity | C13: Alavancagem | D13: 0.92 | E13: 1.02
